{
  "schemaVersion": 1,
  "id": "fabric-mumblelink-mod",
  "version": "${version}",
  "name": "MumbleLink",
  "description": "Positional audio support for Mumble",
  "authors": [
    {
      "name": "Mitchell Skaggs",
      "contact": {
        "email": "skaggsm333@gmail.com"
      }
    }
  ],
  "contact": {
    "homepage": "https://github.com/magneticflux-/fabric-mumblelink-mod",
    "issues": "https://github.com/magneticflux-/fabric-mumblelink-mod/issues",
    "sources": "https://github.com/magneticflux-/fabric-mumblelink-mod"
  },
  "license": "LGPL-3.0-or-later",
  "icon": "assets/fabric-mumblelink-mod/icon.png",
  "environment": "*",
  "entrypoints": {
    "main": [
      {
        "adapter": "kotlin",
        "value": "com.skaggsm.mumblelinkmod.main.MainMumbleLinkMod"
      }
    ],
    "client": [
      {
        "adapter": "kotlin",
        "value": "com.skaggsm.mumblelinkmod.client.ClientMumbleLinkMod"
      }
    ],
    "modmenu": [
      "com.skaggsm.mumblelinkmod.client.MumbleLinkModMenu"
    ]
  },
  "mixins": [
    "fabric-mumblelink-mod.mixins.json"
  ],
  "depends": {
    "fabricloader": ">=0.12.0",
    "fabric": ">=0.36.0",
    "fabric-language-kotlin": ">=1.6.1",
    "minecraft": "1.18.x"
  },
  "suggests": {
    "modmenu": ">=3.0.0"
  }
}
